LICENSE
MANIFEST.in
README.rst
setup.py
init/__init__.py
init/cli.py
init/git.py
init/info.py
init/license.py
init/prompts.py
init/template.py
init.egg-info/PKG-INFO
init.egg-info/SOURCES.txt
init.egg-info/dependency_links.txt
init.egg-info/requires.txt
init.egg-info/top_level.txt
init/licenses/apache.txt
init/licenses/bsd2.txt
init/licenses/bsd3.txt
init/licenses/gpl2.txt
init/licenses/gpl3.txt
init/licenses/mit.txt
scripts/init