Metadata-Version: 1.0
Name: init
Version: 0.1.0
Summary: init the package directory structure
Home-page: https://github.com/lepture/init
Author: Hsiaoming Yang
Author-email: me@lepture.com
License: Copyright (c) 2013, Hsiaoming Yang
